setup.py
wdgameoflife/__main__.py
wdgameoflife/wdgameoflife.py
wdgameoflife.egg-info/PKG-INFO
wdgameoflife.egg-info/SOURCES.txt
wdgameoflife.egg-info/dependency_links.txt
wdgameoflife.egg-info/not-zip-safe
wdgameoflife.egg-info/top_level.txt