Metadata-Version: 1.0
Name: wdgameoflife
Version: 0.0.3
Summary: This is a project for the course Advanced Scientific Programming in Python - Uppsala University
Home-page: https://github.com/wangd3109/wdgameoflife
Author: Duo Wang
Author-email: wangd3109@gmail.com
License: MIT
Platform: UNKNOWN
